ball_game/__init__.py
ball_game/__main__.py
ball_game/assets.py
ball_game/game.py
ball_game-0.2.0.dist-info/LICENSE
ball_game-0.2.0.dist-info/METADATA
ball_game-0.2.0.dist-info/WHEEL
ball_game-0.2.0.dist-info/top_level.txt
ball_game-0.2.0.dist-info/RECORD
