Metadata-Version: 2.1
Name: ball-game
Version: 0.2.0
Summary: Ball Game
Home-page: https://gitlab.com/sergwy/ball_game
Maintainer: Sergey Yakimov
Maintainer-email: sergwy@gmail.com
License: Ball Game
Requires-Python: >=3.8
License-File: LICENSE
Requires-Dist: pygame >=2.1.2
